tap_github/__init__.py
tap_github/authenticator.py
tap_github/client.py
tap_github/organization_streams.py
tap_github/repository_streams.py
tap_github/schema_objects.py
tap_github/scraping.py
tap_github/streams.py
tap_github/tap.py
tap_github/user_streams.py
tap_github/tests/__init__.py
tap_github/tests/conftest.py
tap_github/tests/fixtures.py
tap_github/tests/test_authenticator.py
tap_github/tests/test_core.py
tap_github/tests/test_discover.py
tap_github/tests/test_tap.py
tap_github/utils/__init__.py
tap_github/utils/filter_stdout.py
meltanolabs_tap_github-1.26.0.dist-info/METADATA
meltanolabs_tap_github-1.26.0.dist-info/WHEEL
meltanolabs_tap_github-1.26.0.dist-info/entry_points.txt
meltanolabs_tap_github-1.26.0.dist-info/licenses/LICENSE
meltanolabs_tap_github-1.26.0.dist-info/RECORD
