Metadata-Version: 2.4
Name: meltanolabs-tap-github
Version: 1.26.0
Summary: Singer tap for GitHub, built with the Singer SDK.
Project-URL: Homepage, https://github.com/MeltanoLabs/tap-github
Project-URL: Repository, https://github.com/MeltanoLabs/tap-github
Project-URL: Issue Tracker, https://github.com/MeltanoLabs/tap-github/issues
Author-email: Meltano and Meltano Community <hello@meltano.com>
Maintainer-email: Meltano and Meltano Community <hello@meltano.com>, Edgar Ramírez-Mondragón <edgarrm358@gmail.com>
License-Expression: Apache-2.0
License-File: LICENSE
Keywords: ELT,GitHub,Meltano,Meltano SDK,Singer,Singer SDK
Classifier: Intended Audience :: Developers
Classifier: License :: OSI Approved :: Apache Software License
Classifier: Operating System :: OS Independent
Classifier: Programming Language :: Python :: 3.10
Classifier: Programming Language :: Python :: 3.11
Classifier: Programming Language :: Python :: 3.12
Classifier: Programming Language :: Python :: 3.13
Classifier: Programming Language :: Python :: 3.14
Classifier: Programming Language :: Python :: Implementation :: CPython
Classifier: Typing :: Typed
Requires-Python: >=3.10
Requires-Dist: beautifulsoup4~=4.14.2
Requires-Dist: cryptography~=46.0.1
Requires-Dist: nested-lookup~=0.2.25
Requires-Dist: pyjwt~=2.10.1
Requires-Dist: python-dateutil~=2.9
Requires-Dist: requests~=2.32.3
Requires-Dist: singer-sdk~=0.53.0
